espn-hidden-api/__init__.py
espn-hidden-api/espn.py
espn-hidden-api/tester.py
espn_hidden_api/__init__.py
espn_hidden_api/espn.py
espn_hidden_api/main.py
espn_hidden_api/tester.py
vidstream/__init__.py
vidstream/audio.py
vidstream/streaming.py
espn_hidden_api-0.0.5.dist-info/LICENSE
espn_hidden_api-0.0.5.dist-info/METADATA
espn_hidden_api-0.0.5.dist-info/WHEEL
espn_hidden_api-0.0.5.dist-info/top_level.txt
espn_hidden_api-0.0.5.dist-info/RECORD
